subprocess_tee/__init__.py
subprocess_tee/py.typed
subprocess_tee-0.4.2.dist-info/LICENSE
subprocess_tee-0.4.2.dist-info/METADATA
subprocess_tee-0.4.2.dist-info/WHEEL
subprocess_tee-0.4.2.dist-info/top_level.txt
subprocess_tee-0.4.2.dist-info/RECORD
